MANIFEST.in
README.rst
setup.py
abbreviate/__init__.py
abbreviate/structures.py
abbreviate/version.py
abbreviate.egg-info/PKG-INFO
abbreviate.egg-info/SOURCES.txt
abbreviate.egg-info/dependency_links.txt
abbreviate.egg-info/not-zip-safe
abbreviate.egg-info/requires.txt
abbreviate.egg-info/top_level.txt
abbreviate/resources/__init__.py
abbreviate/resources/abbreviations/__init__.py
abbreviate/resources/abbreviations/en_US.abbr
abbreviate/tests/__init__.py
abbreviate/tests/abbreviate_test.py