Metadata-Version: 1.1
Name: abbreviate
Version: 0.1.1
Summary: Automatically abbreviate text
Home-page: https://github.com/ppannuto/python-abbreviate
Author: Pat Pannuto
Author-email: pat.pannuto+abbreviate@gmail.com
License: MIT
Keywords: string formatting
Platform: UNKNOWN
Classifier: Development Status :: 3 - Alpha
Classifier: Intended Audience :: Developers
Classifier: Programming Language :: Python
Classifier: License :: OSI Approved :: MIT License
Classifier: Natural Language :: English
Classifier: Topic :: Text Processing :: Filters
